datadome_fraud_sdk_python/__init__.py
datadome_fraud_sdk_python/datadome.py
datadome_fraud_sdk_python/model/__init__.py
datadome_fraud_sdk_python/model/address.py
datadome_fraud_sdk_python/model/event.py
datadome_fraud_sdk_python/model/headers.py
datadome_fraud_sdk_python/model/module.py
datadome_fraud_sdk_python/model/operation.py
datadome_fraud_sdk_python/model/user.py
datadome_fraud_sdk_python/model/api/__init__.py
datadome_fraud_sdk_python/model/api/request.py
datadome_fraud_sdk_python/model/api/response.py
datadome_fraud_sdk_python-2.0.1.dist-info/LICENSE
datadome_fraud_sdk_python-2.0.1.dist-info/METADATA
datadome_fraud_sdk_python-2.0.1.dist-info/WHEEL
datadome_fraud_sdk_python-2.0.1.dist-info/top_level.txt
datadome_fraud_sdk_python-2.0.1.dist-info/RECORD
