Metadata-Version: 2.1
Name: datadome_fraud_sdk_python
Version: 2.0.1
Summary: DataDome Fraud Protection - Python SDK
Author-email: DataDome <team.integrations@datadome.co>
Project-URL: Homepage, https://github.com/DataDome/fraud-sdk-python
Project-URL: Documentation, https://docs.datadome.co/docs/account-fraud-protection
Classifier: License :: OSI Approved :: Apache Software License
Classifier: Operating System :: OS Independent
Classifier: Programming Language :: Python :: 3.8
Classifier: Programming Language :: Python :: 3.9
Classifier: Programming Language :: Python :: 3.10
Classifier: Programming Language :: Python :: 3.11
Requires-Python: >=3.8
License-File: LICENSE
Requires-Dist: aiohttp >=3.9.1
